adx_logging/__init__.py
adx_logging/adx_handler.py
adx_logging/client.py
adx_logging/ingest_client.py
adx_python_logging-1.0.0.dist-info/LICENSE
adx_python_logging-1.0.0.dist-info/METADATA
adx_python_logging-1.0.0.dist-info/WHEEL
adx_python_logging-1.0.0.dist-info/top_level.txt
adx_python_logging-1.0.0.dist-info/RECORD
