Metadata-Version: 2.1
Name: adx-python-logging
Version: 1.0.0
Summary: A python logging handler for Azure Data explorer
License-File: LICENSE
Requires-Dist: azure-kusto-data
Requires-Dist: azure.kusto.ingest
Requires-Dist: python-dotenv
